centering_lgram-1.2.2.dist-info/licenses/LICENSE
lgram/__init__.py
lgram/cli.py
lgram/core.py
lgram/models.py
lgram/utils.py
lgram/__pycache__/__init__.cpython-313.pyc
lgram/__pycache__/core.cpython-313.pyc
lgram/models/__init__.py
lgram/models/analyze_transitions.py
lgram/models/auto_correction_finder.py
lgram/models/centering_model.py
lgram/models/centering_theory.py
lgram/models/chunk.py
lgram/models/condordance_model.py
lgram/models/dataset_generator.py
lgram/models/dynamicngramparaphraser.py
lgram/models/get_gender.py
lgram/models/merge_lines.py
lgram/models/model_summary.py
lgram/models/paraphraser.py
lgram/models/performance_optimization_plan.md
lgram/models/preprocessor.py
lgram/models/simple_language_model.py
lgram/models/summary_collocations.py
lgram/models/transition_analyzer.py
lgram/models/transition_pattern_learner.py
lgram/models/utils.py
lgram/models/wrapper.py
lgram/models/__pycache__/__init__.cpython-313.pyc
lgram/models/__pycache__/centering_model.cpython-313.pyc
lgram/models/__pycache__/centering_theory.cpython-313.pyc
lgram/models/__pycache__/chunk.cpython-313.pyc
lgram/models/__pycache__/get_gender.cpython-313.pyc
lgram/models/__pycache__/simple_language_model.cpython-313.pyc
lgram/models/__pycache__/transition_analyzer.cpython-313.pyc
lgram/models/__pycache__/transition_pattern_learner.cpython-313.pyc
lgram/ngrams/bigram_model.pkl
lgram/ngrams/collocations.pkl
lgram/ngrams/corrections.json
lgram/ngrams/fivegram_model.pkl
lgram/ngrams/fourgram_model.pkl
lgram/ngrams/language_model.pkl
lgram/ngrams/more.txt
lgram/ngrams/sixgram_model.pkl
lgram/ngrams/text_data.txt
lgram/ngrams/transition_patterns.json
lgram/ngrams/trigram_model.pkl
models/__init__.py
models/simple_language_model.py
tests/__init__.py
tests/test_lgram.py
centering_lgram-1.2.2.dist-info/METADATA
centering_lgram-1.2.2.dist-info/WHEEL
centering_lgram-1.2.2.dist-info/entry_points.txt
centering_lgram-1.2.2.dist-info/top_level.txt
centering_lgram-1.2.2.dist-info/RECORD
