Metadata-Version: 2.4
Name: centering-lgram
Version: 1.2.2
Summary: Advanced Language Model with Centering Theory for Coherent Text Generation
Home-page: https://github.com/iatagun/Lgram
Author: İlker Atagün
Author-email: İlker Atagün <ilker.atagun@gmail.com>
Project-URL: Homepage, https://github.com/iatagun/Lgram
Project-URL: Bug Reports, https://github.com/iatagun/Lgram/issues
Project-URL: Source, https://github.com/iatagun/Lgram
Project-URL: Documentation, https://github.com/iatagun/Lgram/blob/main/README.md
Keywords: nlp,natural language processing,text generation,centering theory,coherence,language model,n-gram,discourse analysis,computational linguistics
Classifier: Development Status :: 4 - Beta
Classifier: Intended Audience :: Developers
Classifier: Intended Audience :: Science/Research
Classifier: Topic :: Scientific/Engineering :: Artificial Intelligence
Classifier: Topic :: Text Processing :: Linguistic
Classifier: License :: OSI Approved :: MIT License
Classifier: Programming Language :: Python :: 3
Classifier: Programming Language :: Python :: 3.8
Classifier: Programming Language :: Python :: 3.9
Classifier: Programming Language :: Python :: 3.10
Classifier: Programming Language :: Python :: 3.11
Classifier: Programming Language :: Python :: 3.12
Classifier: Operating System :: OS Independent
Requires-Python: >=3.8
License-File: LICENSE
Requires-Dist: torch>=1.9.0
Requires-Dist: transformers>=4.20.0
Requires-Dist: spacy>=3.4.0
Requires-Dist: scikit-learn>=1.0.0
Requires-Dist: scipy>=1.7.0
Requires-Dist: numpy>=1.21.0
Requires-Dist: tqdm>=4.62.0
Provides-Extra: django
Requires-Dist: django>=3.2.0; extra == "django"
Provides-Extra: full
Requires-Dist: django>=3.2.0; extra == "full"
Requires-Dist: jupyter>=1.0.0; extra == "full"
Requires-Dist: matplotlib>=3.5.0; extra == "full"
Requires-Dist: plotly>=5.0.0; extra == "full"
Provides-Extra: dev
Requires-Dist: pytest>=7.0.0; extra == "dev"
Requires-Dist: black>=22.0.0; extra == "dev"
Requires-Dist: flake8>=4.0.0; extra == "dev"
Requires-Dist: mypy>=0.950; extra == "dev"
Requires-Dist: build>=0.8.0; extra == "dev"
Requires-Dist: twine>=4.0.0; extra == "dev"
Dynamic: author
Dynamic: home-page
Dynamic: license-file
Dynamic: requires-python
